<?xml version="1.0" encoding="UTF-8"?>
<!DOCTYPE suite SYSTEM "https://testng.org/testng-1.0.dtd">
<suite name="Suite">
  <test thread-count="5" name="Test">
    <classes>
      <class name="organizationmodule.CreateOrganizationTest"/>
      <class name="contactsmodule.CreateContactWithSupportTest"/>
      <class name="opportunitiesmodule.CreateOpportuinityWithOrganizationAndExpectedCloseDateTest"/>
      <class name="contactsmodule.CreateContactTest"/>
	      <class name="organizationmodule.CreateOrganizationWithTypeTest"/>
      <class name="organizationmodule.CreateOrganizationWithPhoneNoTest"/>
      <class name="opportunitiesmodule.CreateOpportuinityWithOrganizationTest"/>
      <class name="opportunitiesmodule.CreateOpportuinityWithOrganizationAndTypeTest"/>
      <class name="contactsmodule.CreateContactWithOrganizationTest"/>
    </classes>
  </test> <!-- Test -->
</suite> <!-- Suite -->
